python2025/02.black_ruff_wps/complex.py
python2025/03.typing/task1_callable_typevar.py
python2025/03.typing/task2_iterator.py
python2025/__init__.py
python2025/main.py
python2025-0.1.1.dist-info/LICENSE
python2025-0.1.1.dist-info/METADATA
python2025-0.1.1.dist-info/WHEEL
python2025-0.1.1.dist-info/RECORD
